cangjielang/__init__.py
cangjielang/shell/__init__.py
cangjielang/shell/usage.py
cangjielang/src/temp.txt
package_name/__init__.py
package_name/shell/__init__.py
package_name/shell/usage.py
package_name/src/temp.txt
cangjielang-0.0.1.dist-info/LICENSE
cangjielang-0.0.1.dist-info/METADATA
cangjielang-0.0.1.dist-info/WHEEL
cangjielang-0.0.1.dist-info/entry_points.txt
cangjielang-0.0.1.dist-info/top_level.txt
cangjielang-0.0.1.dist-info/zip-safe
cangjielang-0.0.1.dist-info/RECORD
